{
    "name": "graph_aic",
    "input_tensor": [
        "516"
    ],
    "input_shape": [
        {
            "dim": [
                1,
                144,
                20,
                20
            ],
            "dtype": "f16",
            "pack": 0
        }
    ],
    "output_tensor": [
        "538"
    ],
    "output_shape": [
        {
            "dim": [
                1,
                1,
                144,
                400
            ],
            "dtype": "f16",
            "pack": 0
        }
    ],
    "layer": [
        {
            "inst_name": "Reshape_304",
            "type_name": "Reshape3",
            "bottom": [
                "516"
            ],
            "top": [
                "538"
            ],
            "hw": 1,
            "hw_acc": [
                5,
                10,
                15
            ],
            "param": {
                "mode": 2,
                "shape": [
                    1,
                    144,
                    400
                ]
            },
            "sv": 1,
            "data": {
                "input_dtype": 1,
                "output_dtype": 1,
                "input_acc": [
                    5,
                    10,
                    15
                ],
                "output_acc": [
                    5,
                    10,
                    15
                ]
            }
        }
    ]
}